custom_deps/__init__.py
CustomDeps-0.0.2.dist-info/LICENCE
CustomDeps-0.0.2.dist-info/METADATA
CustomDeps-0.0.2.dist-info/WHEEL
CustomDeps-0.0.2.dist-info/top_level.txt
CustomDeps-0.0.2.dist-info/RECORD
