Metadata-Version: 2.1
Name: CustomDeps
Version: 0.0.2
Summary: Manages modules paths and allows importing specific versions of modules designated by Git commit hashes
Home-page: https://github.com/bruot/customdeps
Author: Nicolas Bruot
Author-email: coremeltdown@bruot.org
License: UNKNOWN
Project-URL: Bug Tracker, https://github.com/bruot/customdeps/issues
Platform: UNKNOWN
Classifier: Programming Language :: Python :: 3
Classifier: License :: OSI Approved :: GNU General Public License v3 (GPLv3)
Classifier: Operating System :: OS Independent
Classifier: Intended Audience :: Developers
Classifier: Natural Language :: English
Classifier: Topic :: Software Development :: Libraries :: Python Modules
Classifier: Topic :: Software Development :: Version Control :: Git
Requires-Python: >=3.4
Requires-Dist: appdirs (>=1.3)
Requires-Dist: GitPython (>=2.1)
